README.TXT
README.txt
ez_setup.py
ez_setup.pyc
setup.cfg
setup.py
UploadFu.egg-info/PKG-INFO
UploadFu.egg-info/SOURCES.txt
UploadFu.egg-info/dependency_links.txt
UploadFu.egg-info/not-zip-safe
UploadFu.egg-info/requires.txt
UploadFu.egg-info/top_level.txt
scripts/UploadFu_ContextMenu.py
scripts/UploadFu_Setup.bat
scripts/UploadFu_Setup.py
scripts/UploadFu_StartWatchJobs.py
scripts/UploadFu_Upload.py
scripts/UploadFu_Watch.py
scripts/UploadFu_example.ini
uploadfu/__init__.py
uploadfu/__init__.pyc
uploadfu/BitTorrent/__init__.py
uploadfu/BitTorrent/__init__.pyc
uploadfu/BitTorrent/bencode.py
uploadfu/BitTorrent/bencode.pyc
uploadfu/BitTorrent/btformats.py
uploadfu/BitTorrent/btformats.pyc
uploadfu/BitTorrent/common.py
uploadfu/BitTorrent/makemetafile.py
uploadfu/BitTorrent/makemetafile.pyc
uploadfu/BitTorrent/obsoletepythonsupport.py
uploadfu/BitTorrent/obsoletepythonsupport.pyc
uploadfu/BitTorrent/parseargs.py
uploadfu/BitTorrent/parseargs.pyc