Metadata-Version: 1.0
Name: UploadFu
Version: 0.5
Summary: Bittorrent upload tools for win32
Home-page: UNKNOWN
Author: Leonord
Author-email: allegory.bucket@gmail.com
License: UNKNOWN
Platform: UNKNOWN
Classifier: Development Status :: 3 - Alpha
Classifier: Intended Audience :: System Administrators
Classifier: License :: OSI Approved :: MIT License
Classifier: Operating System :: Microsoft :: Windows
